retry/__init__.py
retry/api.py
retry_extended-0.2.3.dist-info/LICENSE
retry_extended-0.2.3.dist-info/METADATA
retry_extended-0.2.3.dist-info/WHEEL
retry_extended-0.2.3.dist-info/RECORD
